pyCGM_Single/Pipelines.py
pyCGM_Single/__init__.py
pyCGM_Single/_about.py
pyCGM_Single/c3d.py
pyCGM_Single/c3dez.py
pyCGM_Single/c3dpy3.py
pyCGM_Single/clusterCalc.py
pyCGM_Single/pyCGM.py
pyCGM_Single/pyCGM_Helpers.py
pyCGM_Single/pycgmCalc.py
pyCGM_Single/pycgmClusters.py
pyCGM_Single/pycgmIO.py
pyCGM_Single/pycgmKinetics.py
pyCGM_Single/pycgmStatic.py
pyCGM_Single/pycgm_embed.py
pyCGM_Single/runpyCGM.py
pycgm-1.0.dist-info/LICENSE
pycgm-1.0.dist-info/METADATA
pycgm-1.0.dist-info/WHEEL
pycgm-1.0.dist-info/top_level.txt
pycgm-1.0.dist-info/RECORD
