Metadata-Version: 2.1
Name: pycgm
Version: 1.0
Summary: A Python Implementation of the Conventional Gait Model
Home-page: https://github.com/cadop/pycgm
Author: 
Author-email: cadop@umich.edu
License: UNKNOWN
Platform: UNKNOWN
Classifier: Programming Language :: Python :: 3
Classifier: License :: OSI Approved :: MIT License
Classifier: Operating System :: OS Independent
Requires-Python: >=3
Requires-Dist: numpy (>=1.15)
